django_markdownify-0.9.6.dist-info/licenses/LICENSE
markdownify/__init__.py
markdownify/apps.py
markdownify/checks.py
markdownify/templatetags/__init__.py
markdownify/templatetags/markdownify.py
markdownify/tests/__init__.py
markdownify/tests/input_text_alternative.md
markdownify/tests/input_text_bleach.md
markdownify/tests/input_text_default.md
markdownify/tests/input_text_extensions.md
markdownify/tests/input_text_linkify.md
markdownify/tests/input_text_strip.md
markdownify/tests/test_markdownify.py
django_markdownify-0.9.6.dist-info/METADATA
django_markdownify-0.9.6.dist-info/WHEEL
django_markdownify-0.9.6.dist-info/top_level.txt
django_markdownify-0.9.6.dist-info/RECORD
